richer_tqdm/__init__.py
richer_tqdm/richer.py
richer_tqdm-0.0.4.dist-info/LICENSE
richer_tqdm-0.0.4.dist-info/METADATA
richer_tqdm-0.0.4.dist-info/WHEEL
richer_tqdm-0.0.4.dist-info/top_level.txt
richer_tqdm-0.0.4.dist-info/zip-safe
richer_tqdm-0.0.4.dist-info/RECORD
